image_processing/__init__.py
image_processing/image_processing.py
image_processing/py.typed
image_processing/vips_processor.py
image_processing_egg-0.3.1.dist-info/licenses/MIT-LICENSE
image_processing_egg-0.3.1.dist-info/METADATA
image_processing_egg-0.3.1.dist-info/WHEEL
image_processing_egg-0.3.1.dist-info/top_level.txt
image_processing_egg-0.3.1.dist-info/RECORD
