Metadata-Version: 2.4
Name: image-processing-egg
Version: 0.3.1
Summary: High-level image processing wrapper for libvips
Home-page: https://github.com/jpsca/image-processing-egg
Author: Juan-Pablo Scaletti
Author-email: juanpablo@jpscaletti.com
License: MIT
Project-URL: Issue tracker, https://github.com/jpsca/image-processing-egg/issues
Classifier: Development Status :: 4 - Beta
Classifier: Intended Audience :: Developers
Classifier: License :: OSI Approved :: MIT License
Classifier: Programming Language :: Python :: 3.7
Classifier: Programming Language :: Python :: 3.8
Classifier: Programming Language :: Python :: 3.9
Classifier: Programming Language :: Python :: 3.10
Classifier: Topic :: Software Development :: Libraries
Classifier: Topic :: Scientific/Engineering :: Image Processing
Classifier: Typing :: Typed
Requires-Python: <4.0,>=3.7
License-File: MIT-LICENSE
Requires-Dist: pyvips>=2.2.3
Requires-Dist: cffi>=1.17.1
Provides-Extra: test
Requires-Dist: flake8; extra == "test"
Requires-Dist: flake8-bugbear; extra == "test"
Requires-Dist: flake8-logging-format; extra == "test"
Requires-Dist: flake8-quotes; extra == "test"
Requires-Dist: pillow; extra == "test"
Requires-Dist: pytest; extra == "test"
Requires-Dist: pytest-cov; extra == "test"
Requires-Dist: coverage[toml]; extra == "test"
Provides-Extra: dev
Requires-Dist: black; extra == "dev"
Requires-Dist: ipdb; extra == "dev"
Requires-Dist: isort; extra == "dev"
Requires-Dist: pyright; extra == "dev"
Requires-Dist: tox; extra == "dev"
Dynamic: license-file
